simple_pydash/model.py
simple_pydash/server.py
simple_pydash-0.3.5.dist-info/METADATA
simple_pydash-0.3.5.dist-info/WHEEL
simple_pydash-0.3.5.dist-info/top_level.txt
simple_pydash-0.3.5.dist-info/RECORD
