Metadata-Version: 2.1
Name: simple-pydash
Version: 0.3.5
Summary: Lightweight, modular Python library for creating real-time interactive dashboards in the web browser.
Home-page: https://github.com/ValerioB88/simple-pydash
Author: Valerio Biscione
Author-email: valerio.biscione@gmail.com
Classifier: Programming Language :: Python :: 3
Classifier: License :: OSI Approved :: MIT License
Classifier: Operating System :: OS Independent
Requires-Dist: fastapi
Requires-Dist: uvicorn[standard]
Requires-Dist: numpy
Requires-Dist: Pillow
Requires-Dist: plotly
Requires-Dist: sty
Requires-Dist: matplotlib
Requires-Dist: jinja2
